[{"arguments":["clang","-Wno-documentation-unknown-command","-Wno-unknown-warning-option","-Wno-unknown-pragmas","-nostdinc","-nostdinc++","-g","-std=gnu++1z","-Wall","-Wextra","-Wextra","-fexceptions","-mthreads","-fsyntax-only","-m64","--target=x86_64-w64-mingw32","-DUNICODE","-D_UNICODE","-DWIN32","-DMINGW_HAS_SECURE_API","-DQT_QML_DEBUG","-DQT_WIDGETS_LIB","-DQT_GUI_LIB","-DQT_SQL_LIB","-DQT_CORE_LIB","-DQT_NEEDS_QMAIN","-DQ_CREATOR_RUN","-DQT_ANNOTATE_FUNCTION(x)=__attribute__((annotate(#x)))","-ID:\\Qt\\Tools\\QtCreator\\share\\qtcreator\\cplusplus\\wrappedMingwHeaders","-ID:\\Qt\\Tools\\QtCreator\\share\\qtcreator\\cplusplus\\wrappedQtHeaders","-ID:\\Qt\\Tools\\QtCreator\\share\\qtcreator\\cplusplus\\wrappedQtHeaders\\QtCore","-ID:\\qtDocuments\\project3","-ID:\\Qt\\6.7.2\\mingw_64\\include","-ID:\\Qt\\6.7.2\\mingw_64\\include\\QtWidgets","-ID:\\Qt\\6.7.2\\mingw_64\\include\\QtGui","-ID:\\Qt\\6.7.2\\mingw_64\\include\\QtSql","-ID:\\Qt\\6.7.2\\mingw_64\\include\\QtCore","-ID:\\qtDocuments\\project3\\build\\Desktop_Qt_6_7_2_MinGW_64_bit-Debug\\debug","-ID:\\qtDocuments\\project3\\build\\Desktop_Qt_6_7_2_MinGW_64_bit-Debug","-ID:\\Qt\\6.7.2\\mingw_64\\mkspecs\\win32-g++","-isystem","D:\\Qt\\Tools\\mingw1120_64\\lib\\gcc\\x86_64-w64-mingw32\\11.2.0\\include\\c++","-isystem","D:\\Qt\\Tools\\mingw1120_64\\lib\\gcc\\x86_64-w64-mingw32\\11.2.0\\include\\c++\\x86_64-w64-mingw32","-isystem","D:\\Qt\\Tools\\mingw1120_64\\lib\\gcc\\x86_64-w64-mingw32\\11.2.0\\include\\c++\\backward","-isystem","D:\\Qt\\Tools\\QtCreator\\bin\\clang\\lib\\clang\\18\\include","-isystem","D:\\Qt\\Tools\\mingw1120_64\\x86_64-w64-mingw32\\include","-fmessage-length=0","-fdiagnostics-show-note-include-stack","-fretain-comments-from-system-headers","-fmacro-backtrace-limit=0","-ferror-limit=1000","-x","c++","D:\\qtDocuments\\project3\\departmentview.cpp"],"directory":"D:/qtDocuments/project3/build/Desktop_Qt_6_7_2_MinGW_64_bit-Debug/.qtc_clangd","file":"D:/qtDocuments/project3/departmentview.cpp"},{"arguments":["clang","-Wno-documentation-unknown-command","-Wno-unknown-warning-option","-Wno-unknown-pragmas","-nostdinc","-nostdinc++","-g","-std=gnu++1z","-Wall","-Wextra","-Wextra","-fexceptions","-mthreads","-fsyntax-only","-m64","--target=x86_64-w64-mingw32","-DUNICODE","-D_UNICODE","-DWIN32","-DMINGW_HAS_SECURE_API","-DQT_QML_DEBUG","-DQT_WIDGETS_LIB","-DQT_GUI_LIB","-DQT_SQL_LIB","-DQT_CORE_LIB","-DQT_NEEDS_QMAIN","-DQ_CREATOR_RUN","-DQT_ANNOTATE_FUNCTION(x)=__attribute__((annotate(#x)))","-ID:\\Qt\\Tools\\QtCreator\\share\\qtcreator\\cplusplus\\wrappedMingwHeaders","-ID:\\Qt\\Tools\\QtCreator\\share\\qtcreator\\cplusplus\\wrappedQtHeaders","-ID:\\Qt\\Tools\\QtCreator\\share\\qtcreator\\cplusplus\\wrappedQtHeaders\\QtCore","-ID:\\qtDocuments\\project3","-ID:\\Qt\\6.7.2\\mingw_64\\include","-ID:\\Qt\\6.7.2\\mingw_64\\include\\QtWidgets","-ID:\\Qt\\6.7.2\\mingw_64\\include\\QtGui","-ID:\\Qt\\6.7.2\\mingw_64\\include\\QtSql","-ID:\\Qt\\6.7.2\\mingw_64\\include\\QtCore","-ID:\\qtDocuments\\project3\\build\\Desktop_Qt_6_7_2_MinGW_64_bit-Debug\\debug","-ID:\\qtDocuments\\project3\\build\\Desktop_Qt_6_7_2_MinGW_64_bit-Debug","-ID:\\Qt\\6.7.2\\mingw_64\\mkspecs\\win32-g++","-isystem","D:\\Qt\\Tools\\mingw1120_64\\lib\\gcc\\x86_64-w64-mingw32\\11.2.0\\include\\c++","-isystem","D:\\Qt\\Tools\\mingw1120_64\\lib\\gcc\\x86_64-w64-mingw32\\11.2.0\\include\\c++\\x86_64-w64-mingw32","-isystem","D:\\Qt\\Tools\\mingw1120_64\\lib\\gcc\\x86_64-w64-mingw32\\11.2.0\\include\\c++\\backward","-isystem","D:\\Qt\\Tools\\QtCreator\\bin\\clang\\lib\\clang\\18\\include","-isystem","D:\\Qt\\Tools\\mingw1120_64\\x86_64-w64-mingw32\\include","-fmessage-length=0","-fdiagnostics-show-note-include-stack","-fretain-comments-from-system-headers","-fmacro-backtrace-limit=0","-ferror-limit=1000","-x","c++","D:\\qtDocuments\\project3\\doctorview.cpp"],"directory":"D:/qtDocuments/project3/build/Desktop_Qt_6_7_2_MinGW_64_bit-Debug/.qtc_clangd","file":"D:/qtDocuments/project3/doctorview.cpp"},{"arguments":["clang","-Wno-documentation-unknown-command","-Wno-unknown-warning-option","-Wno-unknown-pragmas","-nostdinc","-nostdinc++","-g","-std=gnu++1z","-Wall","-Wextra","-Wextra","-fexceptions","-mthreads","-fsyntax-only","-m64","--target=x86_64-w64-mingw32","-DUNICODE","-D_UNICODE","-DWIN32","-DMINGW_HAS_SECURE_API","-DQT_QML_DEBUG","-DQT_WIDGETS_LIB","-DQT_GUI_LIB","-DQT_SQL_LIB","-DQT_CORE_LIB","-DQT_NEEDS_QMAIN","-DQ_CREATOR_RUN","-DQT_ANNOTATE_FUNCTION(x)=__attribute__((annotate(#x)))","-ID:\\Qt\\Tools\\QtCreator\\share\\qtcreator\\cplusplus\\wrappedMingwHeaders","-ID:\\Qt\\Tools\\QtCreator\\share\\qtcreator\\cplusplus\\wrappedQtHeaders","-ID:\\Qt\\Tools\\QtCreator\\share\\qtcreator\\cplusplus\\wrappedQtHeaders\\QtCore","-ID:\\qtDocuments\\project3","-ID:\\Qt\\6.7.2\\mingw_64\\include","-ID:\\Qt\\6.7.2\\mingw_64\\include\\QtWidgets","-ID:\\Qt\\6.7.2\\mingw_64\\include\\QtGui","-ID:\\Qt\\6.7.2\\mingw_64\\include\\QtSql","-ID:\\Qt\\6.7.2\\mingw_64\\include\\QtCore","-ID:\\qtDocuments\\project3\\build\\Desktop_Qt_6_7_2_MinGW_64_bit-Debug\\debug","-ID:\\qtDocuments\\project3\\build\\Desktop_Qt_6_7_2_MinGW_64_bit-Debug","-ID:\\Qt\\6.7.2\\mingw_64\\mkspecs\\win32-g++","-isystem","D:\\Qt\\Tools\\mingw1120_64\\lib\\gcc\\x86_64-w64-mingw32\\11.2.0\\include\\c++","-isystem","D:\\Qt\\Tools\\mingw1120_64\\lib\\gcc\\x86_64-w64-mingw32\\11.2.0\\include\\c++\\x86_64-w64-mingw32","-isystem","D:\\Qt\\Tools\\mingw1120_64\\lib\\gcc\\x86_64-w64-mingw32\\11.2.0\\include\\c++\\backward","-isystem","D:\\Qt\\Tools\\QtCreator\\bin\\clang\\lib\\clang\\18\\include","-isystem","D:\\Qt\\Tools\\mingw1120_64\\x86_64-w64-mingw32\\include","-fmessage-length=0","-fdiagnostics-show-note-include-stack","-fretain-comments-from-system-headers","-fmacro-backtrace-limit=0","-ferror-limit=1000","-x","c++","D:\\qtDocuments\\project3\\idatabase.cpp"],"directory":"D:/qtDocuments/project3/build/Desktop_Qt_6_7_2_MinGW_64_bit-Debug/.qtc_clangd","file":"D:/qtDocuments/project3/idatabase.cpp"},{"arguments":["clang","-Wno-documentation-unknown-command","-Wno-unknown-warning-option","-Wno-unknown-pragmas","-nostdinc","-nostdinc++","-g","-std=gnu++1z","-Wall","-Wextra","-Wextra","-fexceptions","-mthreads","-fsyntax-only","-m64","--target=x86_64-w64-mingw32","-DUNICODE","-D_UNICODE","-DWIN32","-DMINGW_HAS_SECURE_API","-DQT_QML_DEBUG","-DQT_WIDGETS_LIB","-DQT_GUI_LIB","-DQT_SQL_LIB","-DQT_CORE_LIB","-DQT_NEEDS_QMAIN","-DQ_CREATOR_RUN","-DQT_ANNOTATE_FUNCTION(x)=__attribute__((annotate(#x)))","-ID:\\Qt\\Tools\\QtCreator\\share\\qtcreator\\cplusplus\\wrappedMingwHeaders","-ID:\\Qt\\Tools\\QtCreator\\share\\qtcreator\\cplusplus\\wrappedQtHeaders","-ID:\\Qt\\Tools\\QtCreator\\share\\qtcreator\\cplusplus\\wrappedQtHeaders\\QtCore","-ID:\\qtDocuments\\project3","-ID:\\Qt\\6.7.2\\mingw_64\\include","-ID:\\Qt\\6.7.2\\mingw_64\\include\\QtWidgets","-ID:\\Qt\\6.7.2\\mingw_64\\include\\QtGui","-ID:\\Qt\\6.7.2\\mingw_64\\include\\QtSql","-ID:\\Qt\\6.7.2\\mingw_64\\include\\QtCore","-ID:\\qtDocuments\\project3\\build\\Desktop_Qt_6_7_2_MinGW_64_bit-Debug\\debug","-ID:\\qtDocuments\\project3\\build\\Desktop_Qt_6_7_2_MinGW_64_bit-Debug","-ID:\\Qt\\6.7.2\\mingw_64\\mkspecs\\win32-g++","-isystem","D:\\Qt\\Tools\\mingw1120_64\\lib\\gcc\\x86_64-w64-mingw32\\11.2.0\\include\\c++","-isystem","D:\\Qt\\Tools\\mingw1120_64\\lib\\gcc\\x86_64-w64-mingw32\\11.2.0\\include\\c++\\x86_64-w64-mingw32","-isystem","D:\\Qt\\Tools\\mingw1120_64\\lib\\gcc\\x86_64-w64-mingw32\\11.2.0\\include\\c++\\backward","-isystem","D:\\Qt\\Tools\\QtCreator\\bin\\clang\\lib\\clang\\18\\include","-isystem","D:\\Qt\\Tools\\mingw1120_64\\x86_64-w64-mingw32\\include","-fmessage-length=0","-fdiagnostics-show-note-include-stack","-fretain-comments-from-system-headers","-fmacro-backtrace-limit=0","-ferror-limit=1000","-x","c++","D:\\qtDocuments\\project3\\loginview.cpp"],"directory":"D:/qtDocuments/project3/build/Desktop_Qt_6_7_2_MinGW_64_bit-Debug/.qtc_clangd","file":"D:/qtDocuments/project3/loginview.cpp"},{"arguments":["clang","-Wno-documentation-unknown-command","-Wno-unknown-warning-option","-Wno-unknown-pragmas","-nostdinc","-nostdinc++","-g","-std=gnu++1z","-Wall","-Wextra","-Wextra","-fexceptions","-mthreads","-fsyntax-only","-m64","--target=x86_64-w64-mingw32","-DUNICODE","-D_UNICODE","-DWIN32","-DMINGW_HAS_SECURE_API","-DQT_QML_DEBUG","-DQT_WIDGETS_LIB","-DQT_GUI_LIB","-DQT_SQL_LIB","-DQT_CORE_LIB","-DQT_NEEDS_QMAIN","-DQ_CREATOR_RUN","-DQT_ANNOTATE_FUNCTION(x)=__attribute__((annotate(#x)))","-ID:\\Qt\\Tools\\QtCreator\\share\\qtcreator\\cplusplus\\wrappedMingwHeaders","-ID:\\Qt\\Tools\\QtCreator\\share\\qtcreator\\cplusplus\\wrappedQtHeaders","-ID:\\Qt\\Tools\\QtCreator\\share\\qtcreator\\cplusplus\\wrappedQtHeaders\\QtCore","-ID:\\qtDocuments\\project3","-ID:\\Qt\\6.7.2\\mingw_64\\include","-ID:\\Qt\\6.7.2\\mingw_64\\include\\QtWidgets","-ID:\\Qt\\6.7.2\\mingw_64\\include\\QtGui","-ID:\\Qt\\6.7.2\\mingw_64\\include\\QtSql","-ID:\\Qt\\6.7.2\\mingw_64\\include\\QtCore","-ID:\\qtDocuments\\project3\\build\\Desktop_Qt_6_7_2_MinGW_64_bit-Debug\\debug","-ID:\\qtDocuments\\project3\\build\\Desktop_Qt_6_7_2_MinGW_64_bit-Debug","-ID:\\Qt\\6.7.2\\mingw_64\\mkspecs\\win32-g++","-isystem","D:\\Qt\\Tools\\mingw1120_64\\lib\\gcc\\x86_64-w64-mingw32\\11.2.0\\include\\c++","-isystem","D:\\Qt\\Tools\\mingw1120_64\\lib\\gcc\\x86_64-w64-mingw32\\11.2.0\\include\\c++\\x86_64-w64-mingw32","-isystem","D:\\Qt\\Tools\\mingw1120_64\\lib\\gcc\\x86_64-w64-mingw32\\11.2.0\\include\\c++\\backward","-isystem","D:\\Qt\\Tools\\QtCreator\\bin\\clang\\lib\\clang\\18\\include","-isystem","D:\\Qt\\Tools\\mingw1120_64\\x86_64-w64-mingw32\\include","-fmessage-length=0","-fdiagnostics-show-note-include-stack","-fretain-comments-from-system-headers","-fmacro-backtrace-limit=0","-ferror-limit=1000","-x","c++","D:\\qtDocuments\\project3\\main.cpp"],"directory":"D:/qtDocuments/project3/build/Desktop_Qt_6_7_2_MinGW_64_bit-Debug/.qtc_clangd","file":"D:/qtDocuments/project3/main.cpp"},{"arguments":["clang","-Wno-documentation-unknown-command","-Wno-unknown-warning-option","-Wno-unknown-pragmas","-nostdinc","-nostdinc++","-g","-std=gnu++1z","-Wall","-Wextra","-Wextra","-fexceptions","-mthreads","-fsyntax-only","-m64","--target=x86_64-w64-mingw32","-DUNICODE","-D_UNICODE","-DWIN32","-DMINGW_HAS_SECURE_API","-DQT_QML_DEBUG","-DQT_WIDGETS_LIB","-DQT_GUI_LIB","-DQT_SQL_LIB","-DQT_CORE_LIB","-DQT_NEEDS_QMAIN","-DQ_CREATOR_RUN","-DQT_ANNOTATE_FUNCTION(x)=__attribute__((annotate(#x)))","-ID:\\Qt\\Tools\\QtCreator\\share\\qtcreator\\cplusplus\\wrappedMingwHeaders","-ID:\\Qt\\Tools\\QtCreator\\share\\qtcreator\\cplusplus\\wrappedQtHeaders","-ID:\\Qt\\Tools\\QtCreator\\share\\qtcreator\\cplusplus\\wrappedQtHeaders\\QtCore","-ID:\\qtDocuments\\project3","-ID:\\Qt\\6.7.2\\mingw_64\\include","-ID:\\Qt\\6.7.2\\mingw_64\\include\\QtWidgets","-ID:\\Qt\\6.7.2\\mingw_64\\include\\QtGui","-ID:\\Qt\\6.7.2\\mingw_64\\include\\QtSql","-ID:\\Qt\\6.7.2\\mingw_64\\include\\QtCore","-ID:\\qtDocuments\\project3\\build\\Desktop_Qt_6_7_2_MinGW_64_bit-Debug\\debug","-ID:\\qtDocuments\\project3\\build\\Desktop_Qt_6_7_2_MinGW_64_bit-Debug","-ID:\\Qt\\6.7.2\\mingw_64\\mkspecs\\win32-g++","-isystem","D:\\Qt\\Tools\\mingw1120_64\\lib\\gcc\\x86_64-w64-mingw32\\11.2.0\\include\\c++","-isystem","D:\\Qt\\Tools\\mingw1120_64\\lib\\gcc\\x86_64-w64-mingw32\\11.2.0\\include\\c++\\x86_64-w64-mingw32","-isystem","D:\\Qt\\Tools\\mingw1120_64\\lib\\gcc\\x86_64-w64-mingw32\\11.2.0\\include\\c++\\backward","-isystem","D:\\Qt\\Tools\\QtCreator\\bin\\clang\\lib\\clang\\18\\include","-isystem","D:\\Qt\\Tools\\mingw1120_64\\x86_64-w64-mingw32\\include","-fmessage-length=0","-fdiagnostics-show-note-include-stack","-fretain-comments-from-system-headers","-fmacro-backtrace-limit=0","-ferror-limit=1000","-x","c++","D:\\qtDocuments\\project3\\masterview.cpp"],"directory":"D:/qtDocuments/project3/build/Desktop_Qt_6_7_2_MinGW_64_bit-Debug/.qtc_clangd","file":"D:/qtDocuments/project3/masterview.cpp"},{"arguments":["clang","-Wno-documentation-unknown-command","-Wno-unknown-warning-option","-Wno-unknown-pragmas","-nostdinc","-nostdinc++","-g","-std=gnu++1z","-Wall","-Wextra","-Wextra","-fexceptions","-mthreads","-fsyntax-only","-m64","--target=x86_64-w64-mingw32","-DUNICODE","-D_UNICODE","-DWIN32","-DMINGW_HAS_SECURE_API","-DQT_QML_DEBUG","-DQT_WIDGETS_LIB","-DQT_GUI_LIB","-DQT_SQL_LIB","-DQT_CORE_LIB","-DQT_NEEDS_QMAIN","-DQ_CREATOR_RUN","-DQT_ANNOTATE_FUNCTION(x)=__attribute__((annotate(#x)))","-ID:\\Qt\\Tools\\QtCreator\\share\\qtcreator\\cplusplus\\wrappedMingwHeaders","-ID:\\Qt\\Tools\\QtCreator\\share\\qtcreator\\cplusplus\\wrappedQtHeaders","-ID:\\Qt\\Tools\\QtCreator\\share\\qtcreator\\cplusplus\\wrappedQtHeaders\\QtCore","-ID:\\qtDocuments\\project3","-ID:\\Qt\\6.7.2\\mingw_64\\include","-ID:\\Qt\\6.7.2\\mingw_64\\include\\QtWidgets","-ID:\\Qt\\6.7.2\\mingw_64\\include\\QtGui","-ID:\\Qt\\6.7.2\\mingw_64\\include\\QtSql","-ID:\\Qt\\6.7.2\\mingw_64\\include\\QtCore","-ID:\\qtDocuments\\project3\\build\\Desktop_Qt_6_7_2_MinGW_64_bit-Debug\\debug","-ID:\\qtDocuments\\project3\\build\\Desktop_Qt_6_7_2_MinGW_64_bit-Debug","-ID:\\Qt\\6.7.2\\mingw_64\\mkspecs\\win32-g++","-isystem","D:\\Qt\\Tools\\mingw1120_64\\lib\\gcc\\x86_64-w64-mingw32\\11.2.0\\include\\c++","-isystem","D:\\Qt\\Tools\\mingw1120_64\\lib\\gcc\\x86_64-w64-mingw32\\11.2.0\\include\\c++\\x86_64-w64-mingw32","-isystem","D:\\Qt\\Tools\\mingw1120_64\\lib\\gcc\\x86_64-w64-mingw32\\11.2.0\\include\\c++\\backward","-isystem","D:\\Qt\\Tools\\QtCreator\\bin\\clang\\lib\\clang\\18\\include","-isystem","D:\\Qt\\Tools\\mingw1120_64\\x86_64-w64-mingw32\\include","-fmessage-length=0","-fdiagnostics-show-note-include-stack","-fretain-comments-from-system-headers","-fmacro-backtrace-limit=0","-ferror-limit=1000","-x","c++","D:\\qtDocuments\\project3\\paientview.cpp"],"directory":"D:/qtDocuments/project3/build/Desktop_Qt_6_7_2_MinGW_64_bit-Debug/.qtc_clangd","file":"D:/qtDocuments/project3/paientview.cpp"},{"arguments":["clang","-Wno-documentation-unknown-command","-Wno-unknown-warning-option","-Wno-unknown-pragmas","-nostdinc","-nostdinc++","-g","-std=gnu++1z","-Wall","-Wextra","-Wextra","-fexceptions","-mthreads","-fsyntax-only","-m64","--target=x86_64-w64-mingw32","-DUNICODE","-D_UNICODE","-DWIN32","-DMINGW_HAS_SECURE_API","-DQT_QML_DEBUG","-DQT_WIDGETS_LIB","-DQT_GUI_LIB","-DQT_SQL_LIB","-DQT_CORE_LIB","-DQT_NEEDS_QMAIN","-DQ_CREATOR_RUN","-DQT_ANNOTATE_FUNCTION(x)=__attribute__((annotate(#x)))","-ID:\\Qt\\Tools\\QtCreator\\share\\qtcreator\\cplusplus\\wrappedMingwHeaders","-ID:\\Qt\\Tools\\QtCreator\\share\\qtcreator\\cplusplus\\wrappedQtHeaders","-ID:\\Qt\\Tools\\QtCreator\\share\\qtcreator\\cplusplus\\wrappedQtHeaders\\QtCore","-ID:\\qtDocuments\\project3","-ID:\\Qt\\6.7.2\\mingw_64\\include","-ID:\\Qt\\6.7.2\\mingw_64\\include\\QtWidgets","-ID:\\Qt\\6.7.2\\mingw_64\\include\\QtGui","-ID:\\Qt\\6.7.2\\mingw_64\\include\\QtSql","-ID:\\Qt\\6.7.2\\mingw_64\\include\\QtCore","-ID:\\qtDocuments\\project3\\build\\Desktop_Qt_6_7_2_MinGW_64_bit-Debug\\debug","-ID:\\qtDocuments\\project3\\build\\Desktop_Qt_6_7_2_MinGW_64_bit-Debug","-ID:\\Qt\\6.7.2\\mingw_64\\mkspecs\\win32-g++","-isystem","D:\\Qt\\Tools\\mingw1120_64\\lib\\gcc\\x86_64-w64-mingw32\\11.2.0\\include\\c++","-isystem","D:\\Qt\\Tools\\mingw1120_64\\lib\\gcc\\x86_64-w64-mingw32\\11.2.0\\include\\c++\\x86_64-w64-mingw32","-isystem","D:\\Qt\\Tools\\mingw1120_64\\lib\\gcc\\x86_64-w64-mingw32\\11.2.0\\include\\c++\\backward","-isystem","D:\\Qt\\Tools\\QtCreator\\bin\\clang\\lib\\clang\\18\\include","-isystem","D:\\Qt\\Tools\\mingw1120_64\\x86_64-w64-mingw32\\include","-fmessage-length=0","-fdiagnostics-show-note-include-stack","-fretain-comments-from-system-headers","-fmacro-backtrace-limit=0","-ferror-limit=1000","-x","c++","D:\\qtDocuments\\project3\\patienteditview.cpp"],"directory":"D:/qtDocuments/project3/build/Desktop_Qt_6_7_2_MinGW_64_bit-Debug/.qtc_clangd","file":"D:/qtDocuments/project3/patienteditview.cpp"},{"arguments":["clang","-Wno-documentation-unknown-command","-Wno-unknown-warning-option","-Wno-unknown-pragmas","-nostdinc","-nostdinc++","-g","-std=gnu++1z","-Wall","-Wextra","-Wextra","-fexceptions","-mthreads","-fsyntax-only","-m64","--target=x86_64-w64-mingw32","-DUNICODE","-D_UNICODE","-DWIN32","-DMINGW_HAS_SECURE_API","-DQT_QML_DEBUG","-DQT_WIDGETS_LIB","-DQT_GUI_LIB","-DQT_SQL_LIB","-DQT_CORE_LIB","-DQT_NEEDS_QMAIN","-DQ_CREATOR_RUN","-DQT_ANNOTATE_FUNCTION(x)=__attribute__((annotate(#x)))","-ID:\\Qt\\Tools\\QtCreator\\share\\qtcreator\\cplusplus\\wrappedMingwHeaders","-ID:\\Qt\\Tools\\QtCreator\\share\\qtcreator\\cplusplus\\wrappedQtHeaders","-ID:\\Qt\\Tools\\QtCreator\\share\\qtcreator\\cplusplus\\wrappedQtHeaders\\QtCore","-ID:\\qtDocuments\\project3","-ID:\\Qt\\6.7.2\\mingw_64\\include","-ID:\\Qt\\6.7.2\\mingw_64\\include\\QtWidgets","-ID:\\Qt\\6.7.2\\mingw_64\\include\\QtGui","-ID:\\Qt\\6.7.2\\mingw_64\\include\\QtSql","-ID:\\Qt\\6.7.2\\mingw_64\\include\\QtCore","-ID:\\qtDocuments\\project3\\build\\Desktop_Qt_6_7_2_MinGW_64_bit-Debug\\debug","-ID:\\qtDocuments\\project3\\build\\Desktop_Qt_6_7_2_MinGW_64_bit-Debug","-ID:\\Qt\\6.7.2\\mingw_64\\mkspecs\\win32-g++","-isystem","D:\\Qt\\Tools\\mingw1120_64\\lib\\gcc\\x86_64-w64-mingw32\\11.2.0\\include\\c++","-isystem","D:\\Qt\\Tools\\mingw1120_64\\lib\\gcc\\x86_64-w64-mingw32\\11.2.0\\include\\c++\\x86_64-w64-mingw32","-isystem","D:\\Qt\\Tools\\mingw1120_64\\lib\\gcc\\x86_64-w64-mingw32\\11.2.0\\include\\c++\\backward","-isystem","D:\\Qt\\Tools\\QtCreator\\bin\\clang\\lib\\clang\\18\\include","-isystem","D:\\Qt\\Tools\\mingw1120_64\\x86_64-w64-mingw32\\include","-fmessage-length=0","-fdiagnostics-show-note-include-stack","-fretain-comments-from-system-headers","-fmacro-backtrace-limit=0","-ferror-limit=1000","-x","c++","D:\\qtDocuments\\project3\\welcomeview.cpp"],"directory":"D:/qtDocuments/project3/build/Desktop_Qt_6_7_2_MinGW_64_bit-Debug/.qtc_clangd","file":"D:/qtDocuments/project3/welcomeview.cpp"},{"arguments":["clang","-Wno-documentation-unknown-command","-Wno-unknown-warning-option","-Wno-unknown-pragmas","-nostdinc","-nostdinc++","-g","-std=gnu++1z","-Wall","-Wextra","-Wextra","-fexceptions","-mthreads","-fsyntax-only","-m64","--target=x86_64-w64-mingw32","-DUNICODE","-D_UNICODE","-DWIN32","-DMINGW_HAS_SECURE_API","-DQT_QML_DEBUG","-DQT_WIDGETS_LIB","-DQT_GUI_LIB","-DQT_SQL_LIB","-DQT_CORE_LIB","-DQT_NEEDS_QMAIN","-DQ_CREATOR_RUN","-DQT_ANNOTATE_FUNCTION(x)=__attribute__((annotate(#x)))","-ID:\\Qt\\Tools\\QtCreator\\share\\qtcreator\\cplusplus\\wrappedMingwHeaders","-ID:\\Qt\\Tools\\QtCreator\\share\\qtcreator\\cplusplus\\wrappedQtHeaders","-ID:\\Qt\\Tools\\QtCreator\\share\\qtcreator\\cplusplus\\wrappedQtHeaders\\QtCore","-ID:\\qtDocuments\\project3","-ID:\\Qt\\6.7.2\\mingw_64\\include","-ID:\\Qt\\6.7.2\\mingw_64\\include\\QtWidgets","-ID:\\Qt\\6.7.2\\mingw_64\\include\\QtGui","-ID:\\Qt\\6.7.2\\mingw_64\\include\\QtSql","-ID:\\Qt\\6.7.2\\mingw_64\\include\\QtCore","-ID:\\qtDocuments\\project3\\build\\Desktop_Qt_6_7_2_MinGW_64_bit-Debug\\debug","-ID:\\qtDocuments\\project3\\build\\Desktop_Qt_6_7_2_MinGW_64_bit-Debug","-ID:\\Qt\\6.7.2\\mingw_64\\mkspecs\\win32-g++","-isystem","D:\\Qt\\Tools\\mingw1120_64\\lib\\gcc\\x86_64-w64-mingw32\\11.2.0\\include\\c++","-isystem","D:\\Qt\\Tools\\mingw1120_64\\lib\\gcc\\x86_64-w64-mingw32\\11.2.0\\include\\c++\\x86_64-w64-mingw32","-isystem","D:\\Qt\\Tools\\mingw1120_64\\lib\\gcc\\x86_64-w64-mingw32\\11.2.0\\include\\c++\\backward","-isystem","D:\\Qt\\Tools\\QtCreator\\bin\\clang\\lib\\clang\\18\\include","-isystem","D:\\Qt\\Tools\\mingw1120_64\\x86_64-w64-mingw32\\include","-fmessage-length=0","-fdiagnostics-show-note-include-stack","-fretain-comments-from-system-headers","-fmacro-backtrace-limit=0","-ferror-limit=1000","-x","c++-header","D:\\qtDocuments\\project3\\departmentview.h"],"directory":"D:/qtDocuments/project3/build/Desktop_Qt_6_7_2_MinGW_64_bit-Debug/.qtc_clangd","file":"D:/qtDocuments/project3/departmentview.h"},{"arguments":["clang","-Wno-documentation-unknown-command","-Wno-unknown-warning-option","-Wno-unknown-pragmas","-nostdinc","-nostdinc++","-g","-std=gnu++1z","-Wall","-Wextra","-Wextra","-fexceptions","-mthreads","-fsyntax-only","-m64","--target=x86_64-w64-mingw32","-DUNICODE","-D_UNICODE","-DWIN32","-DMINGW_HAS_SECURE_API","-DQT_QML_DEBUG","-DQT_WIDGETS_LIB","-DQT_GUI_LIB","-DQT_SQL_LIB","-DQT_CORE_LIB","-DQT_NEEDS_QMAIN","-DQ_CREATOR_RUN","-DQT_ANNOTATE_FUNCTION(x)=__attribute__((annotate(#x)))","-ID:\\Qt\\Tools\\QtCreator\\share\\qtcreator\\cplusplus\\wrappedMingwHeaders","-ID:\\Qt\\Tools\\QtCreator\\share\\qtcreator\\cplusplus\\wrappedQtHeaders","-ID:\\Qt\\Tools\\QtCreator\\share\\qtcreator\\cplusplus\\wrappedQtHeaders\\QtCore","-ID:\\qtDocuments\\project3","-ID:\\Qt\\6.7.2\\mingw_64\\include","-ID:\\Qt\\6.7.2\\mingw_64\\include\\QtWidgets","-ID:\\Qt\\6.7.2\\mingw_64\\include\\QtGui","-ID:\\Qt\\6.7.2\\mingw_64\\include\\QtSql","-ID:\\Qt\\6.7.2\\mingw_64\\include\\QtCore","-ID:\\qtDocuments\\project3\\build\\Desktop_Qt_6_7_2_MinGW_64_bit-Debug\\debug","-ID:\\qtDocuments\\project3\\build\\Desktop_Qt_6_7_2_MinGW_64_bit-Debug","-ID:\\Qt\\6.7.2\\mingw_64\\mkspecs\\win32-g++","-isystem","D:\\Qt\\Tools\\mingw1120_64\\lib\\gcc\\x86_64-w64-mingw32\\11.2.0\\include\\c++","-isystem","D:\\Qt\\Tools\\mingw1120_64\\lib\\gcc\\x86_64-w64-mingw32\\11.2.0\\include\\c++\\x86_64-w64-mingw32","-isystem","D:\\Qt\\Tools\\mingw1120_64\\lib\\gcc\\x86_64-w64-mingw32\\11.2.0\\include\\c++\\backward","-isystem","D:\\Qt\\Tools\\QtCreator\\bin\\clang\\lib\\clang\\18\\include","-isystem","D:\\Qt\\Tools\\mingw1120_64\\x86_64-w64-mingw32\\include","-fmessage-length=0","-fdiagnostics-show-note-include-stack","-fretain-comments-from-system-headers","-fmacro-backtrace-limit=0","-ferror-limit=1000","-x","c++-header","D:\\qtDocuments\\project3\\doctorview.h"],"directory":"D:/qtDocuments/project3/build/Desktop_Qt_6_7_2_MinGW_64_bit-Debug/.qtc_clangd","file":"D:/qtDocuments/project3/doctorview.h"},{"arguments":["clang","-Wno-documentation-unknown-command","-Wno-unknown-warning-option","-Wno-unknown-pragmas","-nostdinc","-nostdinc++","-g","-std=gnu++1z","-Wall","-Wextra","-Wextra","-fexceptions","-mthreads","-fsyntax-only","-m64","--target=x86_64-w64-mingw32","-DUNICODE","-D_UNICODE","-DWIN32","-DMINGW_HAS_SECURE_API","-DQT_QML_DEBUG","-DQT_WIDGETS_LIB","-DQT_GUI_LIB","-DQT_SQL_LIB","-DQT_CORE_LIB","-DQT_NEEDS_QMAIN","-DQ_CREATOR_RUN","-DQT_ANNOTATE_FUNCTION(x)=__attribute__((annotate(#x)))","-ID:\\Qt\\Tools\\QtCreator\\share\\qtcreator\\cplusplus\\wrappedMingwHeaders","-ID:\\Qt\\Tools\\QtCreator\\share\\qtcreator\\cplusplus\\wrappedQtHeaders","-ID:\\Qt\\Tools\\QtCreator\\share\\qtcreator\\cplusplus\\wrappedQtHeaders\\QtCore","-ID:\\qtDocuments\\project3","-ID:\\Qt\\6.7.2\\mingw_64\\include","-ID:\\Qt\\6.7.2\\mingw_64\\include\\QtWidgets","-ID:\\Qt\\6.7.2\\mingw_64\\include\\QtGui","-ID:\\Qt\\6.7.2\\mingw_64\\include\\QtSql","-ID:\\Qt\\6.7.2\\mingw_64\\include\\QtCore","-ID:\\qtDocuments\\project3\\build\\Desktop_Qt_6_7_2_MinGW_64_bit-Debug\\debug","-ID:\\qtDocuments\\project3\\build\\Desktop_Qt_6_7_2_MinGW_64_bit-Debug","-ID:\\Qt\\6.7.2\\mingw_64\\mkspecs\\win32-g++","-isystem","D:\\Qt\\Tools\\mingw1120_64\\lib\\gcc\\x86_64-w64-mingw32\\11.2.0\\include\\c++","-isystem","D:\\Qt\\Tools\\mingw1120_64\\lib\\gcc\\x86_64-w64-mingw32\\11.2.0\\include\\c++\\x86_64-w64-mingw32","-isystem","D:\\Qt\\Tools\\mingw1120_64\\lib\\gcc\\x86_64-w64-mingw32\\11.2.0\\include\\c++\\backward","-isystem","D:\\Qt\\Tools\\QtCreator\\bin\\clang\\lib\\clang\\18\\include","-isystem","D:\\Qt\\Tools\\mingw1120_64\\x86_64-w64-mingw32\\include","-fmessage-length=0","-fdiagnostics-show-note-include-stack","-fretain-comments-from-system-headers","-fmacro-backtrace-limit=0","-ferror-limit=1000","-x","c++-header","D:\\qtDocuments\\project3\\idatabase.h"],"directory":"D:/qtDocuments/project3/build/Desktop_Qt_6_7_2_MinGW_64_bit-Debug/.qtc_clangd","file":"D:/qtDocuments/project3/idatabase.h"},{"arguments":["clang","-Wno-documentation-unknown-command","-Wno-unknown-warning-option","-Wno-unknown-pragmas","-nostdinc","-nostdinc++","-g","-std=gnu++1z","-Wall","-Wextra","-Wextra","-fexceptions","-mthreads","-fsyntax-only","-m64","--target=x86_64-w64-mingw32","-DUNICODE","-D_UNICODE","-DWIN32","-DMINGW_HAS_SECURE_API","-DQT_QML_DEBUG","-DQT_WIDGETS_LIB","-DQT_GUI_LIB","-DQT_SQL_LIB","-DQT_CORE_LIB","-DQT_NEEDS_QMAIN","-DQ_CREATOR_RUN","-DQT_ANNOTATE_FUNCTION(x)=__attribute__((annotate(#x)))","-ID:\\Qt\\Tools\\QtCreator\\share\\qtcreator\\cplusplus\\wrappedMingwHeaders","-ID:\\Qt\\Tools\\QtCreator\\share\\qtcreator\\cplusplus\\wrappedQtHeaders","-ID:\\Qt\\Tools\\QtCreator\\share\\qtcreator\\cplusplus\\wrappedQtHeaders\\QtCore","-ID:\\qtDocuments\\project3","-ID:\\Qt\\6.7.2\\mingw_64\\include","-ID:\\Qt\\6.7.2\\mingw_64\\include\\QtWidgets","-ID:\\Qt\\6.7.2\\mingw_64\\include\\QtGui","-ID:\\Qt\\6.7.2\\mingw_64\\include\\QtSql","-ID:\\Qt\\6.7.2\\mingw_64\\include\\QtCore","-ID:\\qtDocuments\\project3\\build\\Desktop_Qt_6_7_2_MinGW_64_bit-Debug\\debug","-ID:\\qtDocuments\\project3\\build\\Desktop_Qt_6_7_2_MinGW_64_bit-Debug","-ID:\\Qt\\6.7.2\\mingw_64\\mkspecs\\win32-g++","-isystem","D:\\Qt\\Tools\\mingw1120_64\\lib\\gcc\\x86_64-w64-mingw32\\11.2.0\\include\\c++","-isystem","D:\\Qt\\Tools\\mingw1120_64\\lib\\gcc\\x86_64-w64-mingw32\\11.2.0\\include\\c++\\x86_64-w64-mingw32","-isystem","D:\\Qt\\Tools\\mingw1120_64\\lib\\gcc\\x86_64-w64-mingw32\\11.2.0\\include\\c++\\backward","-isystem","D:\\Qt\\Tools\\QtCreator\\bin\\clang\\lib\\clang\\18\\include","-isystem","D:\\Qt\\Tools\\mingw1120_64\\x86_64-w64-mingw32\\include","-fmessage-length=0","-fdiagnostics-show-note-include-stack","-fretain-comments-from-system-headers","-fmacro-backtrace-limit=0","-ferror-limit=1000","-x","c++-header","D:\\qtDocuments\\project3\\loginview.h"],"directory":"D:/qtDocuments/project3/build/Desktop_Qt_6_7_2_MinGW_64_bit-Debug/.qtc_clangd","file":"D:/qtDocuments/project3/loginview.h"},{"arguments":["clang","-Wno-documentation-unknown-command","-Wno-unknown-warning-option","-Wno-unknown-pragmas","-nostdinc","-nostdinc++","-g","-std=gnu++1z","-Wall","-Wextra","-Wextra","-fexceptions","-mthreads","-fsyntax-only","-m64","--target=x86_64-w64-mingw32","-DUNICODE","-D_UNICODE","-DWIN32","-DMINGW_HAS_SECURE_API","-DQT_QML_DEBUG","-DQT_WIDGETS_LIB","-DQT_GUI_LIB","-DQT_SQL_LIB","-DQT_CORE_LIB","-DQT_NEEDS_QMAIN","-DQ_CREATOR_RUN","-DQT_ANNOTATE_FUNCTION(x)=__attribute__((annotate(#x)))","-ID:\\Qt\\Tools\\QtCreator\\share\\qtcreator\\cplusplus\\wrappedMingwHeaders","-ID:\\Qt\\Tools\\QtCreator\\share\\qtcreator\\cplusplus\\wrappedQtHeaders","-ID:\\Qt\\Tools\\QtCreator\\share\\qtcreator\\cplusplus\\wrappedQtHeaders\\QtCore","-ID:\\qtDocuments\\project3","-ID:\\Qt\\6.7.2\\mingw_64\\include","-ID:\\Qt\\6.7.2\\mingw_64\\include\\QtWidgets","-ID:\\Qt\\6.7.2\\mingw_64\\include\\QtGui","-ID:\\Qt\\6.7.2\\mingw_64\\include\\QtSql","-ID:\\Qt\\6.7.2\\mingw_64\\include\\QtCore","-ID:\\qtDocuments\\project3\\build\\Desktop_Qt_6_7_2_MinGW_64_bit-Debug\\debug","-ID:\\qtDocuments\\project3\\build\\Desktop_Qt_6_7_2_MinGW_64_bit-Debug","-ID:\\Qt\\6.7.2\\mingw_64\\mkspecs\\win32-g++","-isystem","D:\\Qt\\Tools\\mingw1120_64\\lib\\gcc\\x86_64-w64-mingw32\\11.2.0\\include\\c++","-isystem","D:\\Qt\\Tools\\mingw1120_64\\lib\\gcc\\x86_64-w64-mingw32\\11.2.0\\include\\c++\\x86_64-w64-mingw32","-isystem","D:\\Qt\\Tools\\mingw1120_64\\lib\\gcc\\x86_64-w64-mingw32\\11.2.0\\include\\c++\\backward","-isystem","D:\\Qt\\Tools\\QtCreator\\bin\\clang\\lib\\clang\\18\\include","-isystem","D:\\Qt\\Tools\\mingw1120_64\\x86_64-w64-mingw32\\include","-fmessage-length=0","-fdiagnostics-show-note-include-stack","-fretain-comments-from-system-headers","-fmacro-backtrace-limit=0","-ferror-limit=1000","-x","c++-header","D:\\qtDocuments\\project3\\masterview.h"],"directory":"D:/qtDocuments/project3/build/Desktop_Qt_6_7_2_MinGW_64_bit-Debug/.qtc_clangd","file":"D:/qtDocuments/project3/masterview.h"},{"arguments":["clang","-Wno-documentation-unknown-command","-Wno-unknown-warning-option","-Wno-unknown-pragmas","-nostdinc","-nostdinc++","-g","-std=gnu++1z","-Wall","-Wextra","-Wextra","-fexceptions","-mthreads","-fsyntax-only","-m64","--target=x86_64-w64-mingw32","-DUNICODE","-D_UNICODE","-DWIN32","-DMINGW_HAS_SECURE_API","-DQT_QML_DEBUG","-DQT_WIDGETS_LIB","-DQT_GUI_LIB","-DQT_SQL_LIB","-DQT_CORE_LIB","-DQT_NEEDS_QMAIN","-DQ_CREATOR_RUN","-DQT_ANNOTATE_FUNCTION(x)=__attribute__((annotate(#x)))","-ID:\\Qt\\Tools\\QtCreator\\share\\qtcreator\\cplusplus\\wrappedMingwHeaders","-ID:\\Qt\\Tools\\QtCreator\\share\\qtcreator\\cplusplus\\wrappedQtHeaders","-ID:\\Qt\\Tools\\QtCreator\\share\\qtcreator\\cplusplus\\wrappedQtHeaders\\QtCore","-ID:\\qtDocuments\\project3","-ID:\\Qt\\6.7.2\\mingw_64\\include","-ID:\\Qt\\6.7.2\\mingw_64\\include\\QtWidgets","-ID:\\Qt\\6.7.2\\mingw_64\\include\\QtGui","-ID:\\Qt\\6.7.2\\mingw_64\\include\\QtSql","-ID:\\Qt\\6.7.2\\mingw_64\\include\\QtCore","-ID:\\qtDocuments\\project3\\build\\Desktop_Qt_6_7_2_MinGW_64_bit-Debug\\debug","-ID:\\qtDocuments\\project3\\build\\Desktop_Qt_6_7_2_MinGW_64_bit-Debug","-ID:\\Qt\\6.7.2\\mingw_64\\mkspecs\\win32-g++","-isystem","D:\\Qt\\Tools\\mingw1120_64\\lib\\gcc\\x86_64-w64-mingw32\\11.2.0\\include\\c++","-isystem","D:\\Qt\\Tools\\mingw1120_64\\lib\\gcc\\x86_64-w64-mingw32\\11.2.0\\include\\c++\\x86_64-w64-mingw32","-isystem","D:\\Qt\\Tools\\mingw1120_64\\lib\\gcc\\x86_64-w64-mingw32\\11.2.0\\include\\c++\\backward","-isystem","D:\\Qt\\Tools\\QtCreator\\bin\\clang\\lib\\clang\\18\\include","-isystem","D:\\Qt\\Tools\\mingw1120_64\\x86_64-w64-mingw32\\include","-fmessage-length=0","-fdiagnostics-show-note-include-stack","-fretain-comments-from-system-headers","-fmacro-backtrace-limit=0","-ferror-limit=1000","-x","c++-header","D:\\qtDocuments\\project3\\paientview.h"],"directory":"D:/qtDocuments/project3/build/Desktop_Qt_6_7_2_MinGW_64_bit-Debug/.qtc_clangd","file":"D:/qtDocuments/project3/paientview.h"},{"arguments":["clang","-Wno-documentation-unknown-command","-Wno-unknown-warning-option","-Wno-unknown-pragmas","-nostdinc","-nostdinc++","-g","-std=gnu++1z","-Wall","-Wextra","-Wextra","-fexceptions","-mthreads","-fsyntax-only","-m64","--target=x86_64-w64-mingw32","-DUNICODE","-D_UNICODE","-DWIN32","-DMINGW_HAS_SECURE_API","-DQT_QML_DEBUG","-DQT_WIDGETS_LIB","-DQT_GUI_LIB","-DQT_SQL_LIB","-DQT_CORE_LIB","-DQT_NEEDS_QMAIN","-DQ_CREATOR_RUN","-DQT_ANNOTATE_FUNCTION(x)=__attribute__((annotate(#x)))","-ID:\\Qt\\Tools\\QtCreator\\share\\qtcreator\\cplusplus\\wrappedMingwHeaders","-ID:\\Qt\\Tools\\QtCreator\\share\\qtcreator\\cplusplus\\wrappedQtHeaders","-ID:\\Qt\\Tools\\QtCreator\\share\\qtcreator\\cplusplus\\wrappedQtHeaders\\QtCore","-ID:\\qtDocuments\\project3","-ID:\\Qt\\6.7.2\\mingw_64\\include","-ID:\\Qt\\6.7.2\\mingw_64\\include\\QtWidgets","-ID:\\Qt\\6.7.2\\mingw_64\\include\\QtGui","-ID:\\Qt\\6.7.2\\mingw_64\\include\\QtSql","-ID:\\Qt\\6.7.2\\mingw_64\\include\\QtCore","-ID:\\qtDocuments\\project3\\build\\Desktop_Qt_6_7_2_MinGW_64_bit-Debug\\debug","-ID:\\qtDocuments\\project3\\build\\Desktop_Qt_6_7_2_MinGW_64_bit-Debug","-ID:\\Qt\\6.7.2\\mingw_64\\mkspecs\\win32-g++","-isystem","D:\\Qt\\Tools\\mingw1120_64\\lib\\gcc\\x86_64-w64-mingw32\\11.2.0\\include\\c++","-isystem","D:\\Qt\\Tools\\mingw1120_64\\lib\\gcc\\x86_64-w64-mingw32\\11.2.0\\include\\c++\\x86_64-w64-mingw32","-isystem","D:\\Qt\\Tools\\mingw1120_64\\lib\\gcc\\x86_64-w64-mingw32\\11.2.0\\include\\c++\\backward","-isystem","D:\\Qt\\Tools\\QtCreator\\bin\\clang\\lib\\clang\\18\\include","-isystem","D:\\Qt\\Tools\\mingw1120_64\\x86_64-w64-mingw32\\include","-fmessage-length=0","-fdiagnostics-show-note-include-stack","-fretain-comments-from-system-headers","-fmacro-backtrace-limit=0","-ferror-limit=1000","-x","c++-header","D:\\qtDocuments\\project3\\patienteditview.h"],"directory":"D:/qtDocuments/project3/build/Desktop_Qt_6_7_2_MinGW_64_bit-Debug/.qtc_clangd","file":"D:/qtDocuments/project3/patienteditview.h"},{"arguments":["clang","-Wno-documentation-unknown-command","-Wno-unknown-warning-option","-Wno-unknown-pragmas","-nostdinc","-nostdinc++","-g","-std=gnu++1z","-Wall","-Wextra","-Wextra","-fexceptions","-mthreads","-fsyntax-only","-m64","--target=x86_64-w64-mingw32","-DUNICODE","-D_UNICODE","-DWIN32","-DMINGW_HAS_SECURE_API","-DQT_QML_DEBUG","-DQT_WIDGETS_LIB","-DQT_GUI_LIB","-DQT_SQL_LIB","-DQT_CORE_LIB","-DQT_NEEDS_QMAIN","-DQ_CREATOR_RUN","-DQT_ANNOTATE_FUNCTION(x)=__attribute__((annotate(#x)))","-ID:\\Qt\\Tools\\QtCreator\\share\\qtcreator\\cplusplus\\wrappedMingwHeaders","-ID:\\Qt\\Tools\\QtCreator\\share\\qtcreator\\cplusplus\\wrappedQtHeaders","-ID:\\Qt\\Tools\\QtCreator\\share\\qtcreator\\cplusplus\\wrappedQtHeaders\\QtCore","-ID:\\qtDocuments\\project3","-ID:\\Qt\\6.7.2\\mingw_64\\include","-ID:\\Qt\\6.7.2\\mingw_64\\include\\QtWidgets","-ID:\\Qt\\6.7.2\\mingw_64\\include\\QtGui","-ID:\\Qt\\6.7.2\\mingw_64\\include\\QtSql","-ID:\\Qt\\6.7.2\\mingw_64\\include\\QtCore","-ID:\\qtDocuments\\project3\\build\\Desktop_Qt_6_7_2_MinGW_64_bit-Debug\\debug","-ID:\\qtDocuments\\project3\\build\\Desktop_Qt_6_7_2_MinGW_64_bit-Debug","-ID:\\Qt\\6.7.2\\mingw_64\\mkspecs\\win32-g++","-isystem","D:\\Qt\\Tools\\mingw1120_64\\lib\\gcc\\x86_64-w64-mingw32\\11.2.0\\include\\c++","-isystem","D:\\Qt\\Tools\\mingw1120_64\\lib\\gcc\\x86_64-w64-mingw32\\11.2.0\\include\\c++\\x86_64-w64-mingw32","-isystem","D:\\Qt\\Tools\\mingw1120_64\\lib\\gcc\\x86_64-w64-mingw32\\11.2.0\\include\\c++\\backward","-isystem","D:\\Qt\\Tools\\QtCreator\\bin\\clang\\lib\\clang\\18\\include","-isystem","D:\\Qt\\Tools\\mingw1120_64\\x86_64-w64-mingw32\\include","-fmessage-length=0","-fdiagnostics-show-note-include-stack","-fretain-comments-from-system-headers","-fmacro-backtrace-limit=0","-ferror-limit=1000","-x","c++-header","D:\\qtDocuments\\project3\\welcomeview.h"],"directory":"D:/qtDocuments/project3/build/Desktop_Qt_6_7_2_MinGW_64_bit-Debug/.qtc_clangd","file":"D:/qtDocuments/project3/welcomeview.h"},{"arguments":["clang","-Wno-documentation-unknown-command","-Wno-unknown-warning-option","-Wno-unknown-pragmas","-nostdinc","-nostdinc++","-g","-std=gnu++1z","-Wall","-Wextra","-Wextra","-fexceptions","-mthreads","-fsyntax-only","-m64","--target=x86_64-w64-mingw32","-DUNICODE","-D_UNICODE","-DWIN32","-DMINGW_HAS_SECURE_API","-DQT_QML_DEBUG","-DQT_WIDGETS_LIB","-DQT_GUI_LIB","-DQT_SQL_LIB","-DQT_CORE_LIB","-DQT_NEEDS_QMAIN","-DQ_CREATOR_RUN","-DQT_ANNOTATE_FUNCTION(x)=__attribute__((annotate(#x)))","-ID:\\Qt\\Tools\\QtCreator\\share\\qtcreator\\cplusplus\\wrappedMingwHeaders","-ID:\\Qt\\Tools\\QtCreator\\share\\qtcreator\\cplusplus\\wrappedQtHeaders","-ID:\\Qt\\Tools\\QtCreator\\share\\qtcreator\\cplusplus\\wrappedQtHeaders\\QtCore","-ID:\\qtDocuments\\project3","-ID:\\Qt\\6.7.2\\mingw_64\\include","-ID:\\Qt\\6.7.2\\mingw_64\\include\\QtWidgets","-ID:\\Qt\\6.7.2\\mingw_64\\include\\QtGui","-ID:\\Qt\\6.7.2\\mingw_64\\include\\QtSql","-ID:\\Qt\\6.7.2\\mingw_64\\include\\QtCore","-ID:\\qtDocuments\\project3\\build\\Desktop_Qt_6_7_2_MinGW_64_bit-Debug\\debug","-ID:\\qtDocuments\\project3\\build\\Desktop_Qt_6_7_2_MinGW_64_bit-Debug","-ID:\\Qt\\6.7.2\\mingw_64\\mkspecs\\win32-g++","-isystem","D:\\Qt\\Tools\\mingw1120_64\\lib\\gcc\\x86_64-w64-mingw32\\11.2.0\\include\\c++","-isystem","D:\\Qt\\Tools\\mingw1120_64\\lib\\gcc\\x86_64-w64-mingw32\\11.2.0\\include\\c++\\x86_64-w64-mingw32","-isystem","D:\\Qt\\Tools\\mingw1120_64\\lib\\gcc\\x86_64-w64-mingw32\\11.2.0\\include\\c++\\backward","-isystem","D:\\Qt\\Tools\\QtCreator\\bin\\clang\\lib\\clang\\18\\include","-isystem","D:\\Qt\\Tools\\mingw1120_64\\x86_64-w64-mingw32\\include","-fmessage-length=0","-fdiagnostics-show-note-include-stack","-fretain-comments-from-system-headers","-fmacro-backtrace-limit=0","-ferror-limit=1000","-x","c++-header","D:\\qtDocuments\\project3\\build\\Desktop_Qt_6_7_2_MinGW_64_bit-Debug\\ui_patienteditview.h"],"directory":"D:/qtDocuments/project3/build/Desktop_Qt_6_7_2_MinGW_64_bit-Debug/.qtc_clangd","file":"D:/qtDocuments/project3/build/Desktop_Qt_6_7_2_MinGW_64_bit-Debug/ui_patienteditview.h"},{"arguments":["clang","-Wno-documentation-unknown-command","-Wno-unknown-warning-option","-Wno-unknown-pragmas","-nostdinc","-nostdinc++","-g","-std=gnu++1z","-Wall","-Wextra","-Wextra","-fexceptions","-mthreads","-fsyntax-only","-m64","--target=x86_64-w64-mingw32","-DUNICODE","-D_UNICODE","-DWIN32","-DMINGW_HAS_SECURE_API","-DQT_QML_DEBUG","-DQT_WIDGETS_LIB","-DQT_GUI_LIB","-DQT_SQL_LIB","-DQT_CORE_LIB","-DQT_NEEDS_QMAIN","-DQ_CREATOR_RUN","-DQT_ANNOTATE_FUNCTION(x)=__attribute__((annotate(#x)))","-ID:\\Qt\\Tools\\QtCreator\\share\\qtcreator\\cplusplus\\wrappedMingwHeaders","-ID:\\Qt\\Tools\\QtCreator\\share\\qtcreator\\cplusplus\\wrappedQtHeaders","-ID:\\Qt\\Tools\\QtCreator\\share\\qtcreator\\cplusplus\\wrappedQtHeaders\\QtCore","-ID:\\qtDocuments\\project3","-ID:\\Qt\\6.7.2\\mingw_64\\include","-ID:\\Qt\\6.7.2\\mingw_64\\include\\QtWidgets","-ID:\\Qt\\6.7.2\\mingw_64\\include\\QtGui","-ID:\\Qt\\6.7.2\\mingw_64\\include\\QtSql","-ID:\\Qt\\6.7.2\\mingw_64\\include\\QtCore","-ID:\\qtDocuments\\project3\\build\\Desktop_Qt_6_7_2_MinGW_64_bit-Debug\\debug","-ID:\\qtDocuments\\project3\\build\\Desktop_Qt_6_7_2_MinGW_64_bit-Debug","-ID:\\Qt\\6.7.2\\mingw_64\\mkspecs\\win32-g++","-isystem","D:\\Qt\\Tools\\mingw1120_64\\lib\\gcc\\x86_64-w64-mingw32\\11.2.0\\include\\c++","-isystem","D:\\Qt\\Tools\\mingw1120_64\\lib\\gcc\\x86_64-w64-mingw32\\11.2.0\\include\\c++\\x86_64-w64-mingw32","-isystem","D:\\Qt\\Tools\\mingw1120_64\\lib\\gcc\\x86_64-w64-mingw32\\11.2.0\\include\\c++\\backward","-isystem","D:\\Qt\\Tools\\QtCreator\\bin\\clang\\lib\\clang\\18\\include","-isystem","D:\\Qt\\Tools\\mingw1120_64\\x86_64-w64-mingw32\\include","-fmessage-length=0","-fdiagnostics-show-note-include-stack","-fretain-comments-from-system-headers","-fmacro-backtrace-limit=0","-ferror-limit=1000","-x","c++-header","D:\\qtDocuments\\project3\\build\\Desktop_Qt_6_7_2_MinGW_64_bit-Debug\\ui_welcomeview.h"],"directory":"D:/qtDocuments/project3/build/Desktop_Qt_6_7_2_MinGW_64_bit-Debug/.qtc_clangd","file":"D:/qtDocuments/project3/build/Desktop_Qt_6_7_2_MinGW_64_bit-Debug/ui_welcomeview.h"},{"arguments":["clang","-Wno-documentation-unknown-command","-Wno-unknown-warning-option","-Wno-unknown-pragmas","-nostdinc","-nostdinc++","-g","-std=gnu++1z","-Wall","-Wextra","-Wextra","-fexceptions","-mthreads","-fsyntax-only","-m64","--target=x86_64-w64-mingw32","-DUNICODE","-D_UNICODE","-DWIN32","-DMINGW_HAS_SECURE_API","-DQT_QML_DEBUG","-DQT_WIDGETS_LIB","-DQT_GUI_LIB","-DQT_SQL_LIB","-DQT_CORE_LIB","-DQT_NEEDS_QMAIN","-DQ_CREATOR_RUN","-DQT_ANNOTATE_FUNCTION(x)=__attribute__((annotate(#x)))","-ID:\\Qt\\Tools\\QtCreator\\share\\qtcreator\\cplusplus\\wrappedMingwHeaders","-ID:\\Qt\\Tools\\QtCreator\\share\\qtcreator\\cplusplus\\wrappedQtHeaders","-ID:\\Qt\\Tools\\QtCreator\\share\\qtcreator\\cplusplus\\wrappedQtHeaders\\QtCore","-ID:\\qtDocuments\\project3","-ID:\\Qt\\6.7.2\\mingw_64\\include","-ID:\\Qt\\6.7.2\\mingw_64\\include\\QtWidgets","-ID:\\Qt\\6.7.2\\mingw_64\\include\\QtGui","-ID:\\Qt\\6.7.2\\mingw_64\\include\\QtSql","-ID:\\Qt\\6.7.2\\mingw_64\\include\\QtCore","-ID:\\qtDocuments\\project3\\build\\Desktop_Qt_6_7_2_MinGW_64_bit-Debug\\debug","-ID:\\qtDocuments\\project3\\build\\Desktop_Qt_6_7_2_MinGW_64_bit-Debug","-ID:\\Qt\\6.7.2\\mingw_64\\mkspecs\\win32-g++","-isystem","D:\\Qt\\Tools\\mingw1120_64\\lib\\gcc\\x86_64-w64-mingw32\\11.2.0\\include\\c++","-isystem","D:\\Qt\\Tools\\mingw1120_64\\lib\\gcc\\x86_64-w64-mingw32\\11.2.0\\include\\c++\\x86_64-w64-mingw32","-isystem","D:\\Qt\\Tools\\mingw1120_64\\lib\\gcc\\x86_64-w64-mingw32\\11.2.0\\include\\c++\\backward","-isystem","D:\\Qt\\Tools\\QtCreator\\bin\\clang\\lib\\clang\\18\\include","-isystem","D:\\Qt\\Tools\\mingw1120_64\\x86_64-w64-mingw32\\include","-fmessage-length=0","-fdiagnostics-show-note-include-stack","-fretain-comments-from-system-headers","-fmacro-backtrace-limit=0","-ferror-limit=1000","-x","c++-header","D:\\qtDocuments\\project3\\build\\Desktop_Qt_6_7_2_MinGW_64_bit-Debug\\ui_doctorview.h"],"directory":"D:/qtDocuments/project3/build/Desktop_Qt_6_7_2_MinGW_64_bit-Debug/.qtc_clangd","file":"D:/qtDocuments/project3/build/Desktop_Qt_6_7_2_MinGW_64_bit-Debug/ui_doctorview.h"},{"arguments":["clang","-Wno-documentation-unknown-command","-Wno-unknown-warning-option","-Wno-unknown-pragmas","-nostdinc","-nostdinc++","-g","-std=gnu++1z","-Wall","-Wextra","-Wextra","-fexceptions","-mthreads","-fsyntax-only","-m64","--target=x86_64-w64-mingw32","-DUNICODE","-D_UNICODE","-DWIN32","-DMINGW_HAS_SECURE_API","-DQT_QML_DEBUG","-DQT_WIDGETS_LIB","-DQT_GUI_LIB","-DQT_SQL_LIB","-DQT_CORE_LIB","-DQT_NEEDS_QMAIN","-DQ_CREATOR_RUN","-DQT_ANNOTATE_FUNCTION(x)=__attribute__((annotate(#x)))","-ID:\\Qt\\Tools\\QtCreator\\share\\qtcreator\\cplusplus\\wrappedMingwHeaders","-ID:\\Qt\\Tools\\QtCreator\\share\\qtcreator\\cplusplus\\wrappedQtHeaders","-ID:\\Qt\\Tools\\QtCreator\\share\\qtcreator\\cplusplus\\wrappedQtHeaders\\QtCore","-ID:\\qtDocuments\\project3","-ID:\\Qt\\6.7.2\\mingw_64\\include","-ID:\\Qt\\6.7.2\\mingw_64\\include\\QtWidgets","-ID:\\Qt\\6.7.2\\mingw_64\\include\\QtGui","-ID:\\Qt\\6.7.2\\mingw_64\\include\\QtSql","-ID:\\Qt\\6.7.2\\mingw_64\\include\\QtCore","-ID:\\qtDocuments\\project3\\build\\Desktop_Qt_6_7_2_MinGW_64_bit-Debug\\debug","-ID:\\qtDocuments\\project3\\build\\Desktop_Qt_6_7_2_MinGW_64_bit-Debug","-ID:\\Qt\\6.7.2\\mingw_64\\mkspecs\\win32-g++","-isystem","D:\\Qt\\Tools\\mingw1120_64\\lib\\gcc\\x86_64-w64-mingw32\\11.2.0\\include\\c++","-isystem","D:\\Qt\\Tools\\mingw1120_64\\lib\\gcc\\x86_64-w64-mingw32\\11.2.0\\include\\c++\\x86_64-w64-mingw32","-isystem","D:\\Qt\\Tools\\mingw1120_64\\lib\\gcc\\x86_64-w64-mingw32\\11.2.0\\include\\c++\\backward","-isystem","D:\\Qt\\Tools\\QtCreator\\bin\\clang\\lib\\clang\\18\\include","-isystem","D:\\Qt\\Tools\\mingw1120_64\\x86_64-w64-mingw32\\include","-fmessage-length=0","-fdiagnostics-show-note-include-stack","-fretain-comments-from-system-headers","-fmacro-backtrace-limit=0","-ferror-limit=1000","-x","c++-header","D:\\qtDocuments\\project3\\build\\Desktop_Qt_6_7_2_MinGW_64_bit-Debug\\ui_departmentview.h"],"directory":"D:/qtDocuments/project3/build/Desktop_Qt_6_7_2_MinGW_64_bit-Debug/.qtc_clangd","file":"D:/qtDocuments/project3/build/Desktop_Qt_6_7_2_MinGW_64_bit-Debug/ui_departmentview.h"},{"arguments":["clang","-Wno-documentation-unknown-command","-Wno-unknown-warning-option","-Wno-unknown-pragmas","-nostdinc","-nostdinc++","-g","-std=gnu++1z","-Wall","-Wextra","-Wextra","-fexceptions","-mthreads","-fsyntax-only","-m64","--target=x86_64-w64-mingw32","-DUNICODE","-D_UNICODE","-DWIN32","-DMINGW_HAS_SECURE_API","-DQT_QML_DEBUG","-DQT_WIDGETS_LIB","-DQT_GUI_LIB","-DQT_SQL_LIB","-DQT_CORE_LIB","-DQT_NEEDS_QMAIN","-DQ_CREATOR_RUN","-DQT_ANNOTATE_FUNCTION(x)=__attribute__((annotate(#x)))","-ID:\\Qt\\Tools\\QtCreator\\share\\qtcreator\\cplusplus\\wrappedMingwHeaders","-ID:\\Qt\\Tools\\QtCreator\\share\\qtcreator\\cplusplus\\wrappedQtHeaders","-ID:\\Qt\\Tools\\QtCreator\\share\\qtcreator\\cplusplus\\wrappedQtHeaders\\QtCore","-ID:\\qtDocuments\\project3","-ID:\\Qt\\6.7.2\\mingw_64\\include","-ID:\\Qt\\6.7.2\\mingw_64\\include\\QtWidgets","-ID:\\Qt\\6.7.2\\mingw_64\\include\\QtGui","-ID:\\Qt\\6.7.2\\mingw_64\\include\\QtSql","-ID:\\Qt\\6.7.2\\mingw_64\\include\\QtCore","-ID:\\qtDocuments\\project3\\build\\Desktop_Qt_6_7_2_MinGW_64_bit-Debug\\debug","-ID:\\qtDocuments\\project3\\build\\Desktop_Qt_6_7_2_MinGW_64_bit-Debug","-ID:\\Qt\\6.7.2\\mingw_64\\mkspecs\\win32-g++","-isystem","D:\\Qt\\Tools\\mingw1120_64\\lib\\gcc\\x86_64-w64-mingw32\\11.2.0\\include\\c++","-isystem","D:\\Qt\\Tools\\mingw1120_64\\lib\\gcc\\x86_64-w64-mingw32\\11.2.0\\include\\c++\\x86_64-w64-mingw32","-isystem","D:\\Qt\\Tools\\mingw1120_64\\lib\\gcc\\x86_64-w64-mingw32\\11.2.0\\include\\c++\\backward","-isystem","D:\\Qt\\Tools\\QtCreator\\bin\\clang\\lib\\clang\\18\\include","-isystem","D:\\Qt\\Tools\\mingw1120_64\\x86_64-w64-mingw32\\include","-fmessage-length=0","-fdiagnostics-show-note-include-stack","-fretain-comments-from-system-headers","-fmacro-backtrace-limit=0","-ferror-limit=1000","-x","c++-header","D:\\qtDocuments\\project3\\build\\Desktop_Qt_6_7_2_MinGW_64_bit-Debug\\ui_masterview.h"],"directory":"D:/qtDocuments/project3/build/Desktop_Qt_6_7_2_MinGW_64_bit-Debug/.qtc_clangd","file":"D:/qtDocuments/project3/build/Desktop_Qt_6_7_2_MinGW_64_bit-Debug/ui_masterview.h"},{"arguments":["clang","-Wno-documentation-unknown-command","-Wno-unknown-warning-option","-Wno-unknown-pragmas","-nostdinc","-nostdinc++","-g","-std=gnu++1z","-Wall","-Wextra","-Wextra","-fexceptions","-mthreads","-fsyntax-only","-m64","--target=x86_64-w64-mingw32","-DUNICODE","-D_UNICODE","-DWIN32","-DMINGW_HAS_SECURE_API","-DQT_QML_DEBUG","-DQT_WIDGETS_LIB","-DQT_GUI_LIB","-DQT_SQL_LIB","-DQT_CORE_LIB","-DQT_NEEDS_QMAIN","-DQ_CREATOR_RUN","-DQT_ANNOTATE_FUNCTION(x)=__attribute__((annotate(#x)))","-ID:\\Qt\\Tools\\QtCreator\\share\\qtcreator\\cplusplus\\wrappedMingwHeaders","-ID:\\Qt\\Tools\\QtCreator\\share\\qtcreator\\cplusplus\\wrappedQtHeaders","-ID:\\Qt\\Tools\\QtCreator\\share\\qtcreator\\cplusplus\\wrappedQtHeaders\\QtCore","-ID:\\qtDocuments\\project3","-ID:\\Qt\\6.7.2\\mingw_64\\include","-ID:\\Qt\\6.7.2\\mingw_64\\include\\QtWidgets","-ID:\\Qt\\6.7.2\\mingw_64\\include\\QtGui","-ID:\\Qt\\6.7.2\\mingw_64\\include\\QtSql","-ID:\\Qt\\6.7.2\\mingw_64\\include\\QtCore","-ID:\\qtDocuments\\project3\\build\\Desktop_Qt_6_7_2_MinGW_64_bit-Debug\\debug","-ID:\\qtDocuments\\project3\\build\\Desktop_Qt_6_7_2_MinGW_64_bit-Debug","-ID:\\Qt\\6.7.2\\mingw_64\\mkspecs\\win32-g++","-isystem","D:\\Qt\\Tools\\mingw1120_64\\lib\\gcc\\x86_64-w64-mingw32\\11.2.0\\include\\c++","-isystem","D:\\Qt\\Tools\\mingw1120_64\\lib\\gcc\\x86_64-w64-mingw32\\11.2.0\\include\\c++\\x86_64-w64-mingw32","-isystem","D:\\Qt\\Tools\\mingw1120_64\\lib\\gcc\\x86_64-w64-mingw32\\11.2.0\\include\\c++\\backward","-isystem","D:\\Qt\\Tools\\QtCreator\\bin\\clang\\lib\\clang\\18\\include","-isystem","D:\\Qt\\Tools\\mingw1120_64\\x86_64-w64-mingw32\\include","-fmessage-length=0","-fdiagnostics-show-note-include-stack","-fretain-comments-from-system-headers","-fmacro-backtrace-limit=0","-ferror-limit=1000","-x","c++-header","D:\\qtDocuments\\project3\\build\\Desktop_Qt_6_7_2_MinGW_64_bit-Debug\\ui_loginview.h"],"directory":"D:/qtDocuments/project3/build/Desktop_Qt_6_7_2_MinGW_64_bit-Debug/.qtc_clangd","file":"D:/qtDocuments/project3/build/Desktop_Qt_6_7_2_MinGW_64_bit-Debug/ui_loginview.h"},{"arguments":["clang","-Wno-documentation-unknown-command","-Wno-unknown-warning-option","-Wno-unknown-pragmas","-nostdinc","-nostdinc++","-g","-std=gnu++1z","-Wall","-Wextra","-Wextra","-fexceptions","-mthreads","-fsyntax-only","-m64","--target=x86_64-w64-mingw32","-DUNICODE","-D_UNICODE","-DWIN32","-DMINGW_HAS_SECURE_API","-DQT_QML_DEBUG","-DQT_WIDGETS_LIB","-DQT_GUI_LIB","-DQT_SQL_LIB","-DQT_CORE_LIB","-DQT_NEEDS_QMAIN","-DQ_CREATOR_RUN","-DQT_ANNOTATE_FUNCTION(x)=__attribute__((annotate(#x)))","-ID:\\Qt\\Tools\\QtCreator\\share\\qtcreator\\cplusplus\\wrappedMingwHeaders","-ID:\\Qt\\Tools\\QtCreator\\share\\qtcreator\\cplusplus\\wrappedQtHeaders","-ID:\\Qt\\Tools\\QtCreator\\share\\qtcreator\\cplusplus\\wrappedQtHeaders\\QtCore","-ID:\\qtDocuments\\project3","-ID:\\Qt\\6.7.2\\mingw_64\\include","-ID:\\Qt\\6.7.2\\mingw_64\\include\\QtWidgets","-ID:\\Qt\\6.7.2\\mingw_64\\include\\QtGui","-ID:\\Qt\\6.7.2\\mingw_64\\include\\QtSql","-ID:\\Qt\\6.7.2\\mingw_64\\include\\QtCore","-ID:\\qtDocuments\\project3\\build\\Desktop_Qt_6_7_2_MinGW_64_bit-Debug\\debug","-ID:\\qtDocuments\\project3\\build\\Desktop_Qt_6_7_2_MinGW_64_bit-Debug","-ID:\\Qt\\6.7.2\\mingw_64\\mkspecs\\win32-g++","-isystem","D:\\Qt\\Tools\\mingw1120_64\\lib\\gcc\\x86_64-w64-mingw32\\11.2.0\\include\\c++","-isystem","D:\\Qt\\Tools\\mingw1120_64\\lib\\gcc\\x86_64-w64-mingw32\\11.2.0\\include\\c++\\x86_64-w64-mingw32","-isystem","D:\\Qt\\Tools\\mingw1120_64\\lib\\gcc\\x86_64-w64-mingw32\\11.2.0\\include\\c++\\backward","-isystem","D:\\Qt\\Tools\\QtCreator\\bin\\clang\\lib\\clang\\18\\include","-isystem","D:\\Qt\\Tools\\mingw1120_64\\x86_64-w64-mingw32\\include","-fmessage-length=0","-fdiagnostics-show-note-include-stack","-fretain-comments-from-system-headers","-fmacro-backtrace-limit=0","-ferror-limit=1000","-x","c++-header","D:\\qtDocuments\\project3\\build\\Desktop_Qt_6_7_2_MinGW_64_bit-Debug\\ui_paientview.h"],"directory":"D:/qtDocuments/project3/build/Desktop_Qt_6_7_2_MinGW_64_bit-Debug/.qtc_clangd","file":"D:/qtDocuments/project3/build/Desktop_Qt_6_7_2_MinGW_64_bit-Debug/ui_paientview.h"}]